jitt.py
jitt-0.1.0.dist-info/LICENSE
jitt-0.1.0.dist-info/METADATA
jitt-0.1.0.dist-info/WHEEL
jitt-0.1.0.dist-info/top_level.txt
jitt-0.1.0.dist-info/RECORD
