Metadata-Version: 2.1
Name: jitt
Version: 0.1.0
Summary: Takes a baseline delay value, a percentage to calculate the min/max for allowed jitter values, and a desired precision; returns a float.
Home-page: https://github.com/bonifield/jitt
Author: James Bonifield
Author-email: bonifield.tools@gmail.com
License: UNKNOWN
Platform: UNKNOWN
Classifier: Programming Language :: Python :: 3
Classifier: License :: OSI Approved :: MIT License
Classifier: Operating System :: OS Independent
License-File: LICENSE
